[
    {
        "title": "【原神】神鹤砂心-日常大世界环境输出手法练习",
        "desc": "【原神】神鹤砂心-日常大世界环境输出手法练习，对于没有万叶的神里永冻队玩家，萌新小白们可选择参考输出手法，相对于另一队神里永冻配队--神鹤莫迪来说，宫心海的持续长时间稳定挂水能力，以及相对简单的输出流转手法，能持续提供稳定的每单次伤害输出（神鹤莫迪永冻队日常输出手法练习视频后续将传会录制放出）。\n\n日常游戏练习随机录制的视频，喜欢三连，不喜欢勿喷。",
        "url": "http://www.bilibili.com/video/av487122538",
        "pic": "https://i1.hdslb.com/bfs/archive/fcc815d5461cd6e401ebedbcb1d53e8987ffaaf3.jpg",
        "author": "天山脚下隐居士",
        "play": 2,
        "favorites": 0,
        "duration": "0:50",
        "pubdate": 1686201492
    },
    {
        "title": "印度恒河大桥直播中垮塌，火车撞击事故仍在处理，不可思议的印度，再一次让人感到不可思议",
        "desc": "-",
        "url": "http://www.bilibili.com/video/av784007013",
        "pic": "https://i1.hdslb.com/bfs/archive/e57c66758f8a8839cdad74f940c362bbe342005a.jpg",
        "author": "大卫科波菲尔奥力给",
        "play": 763,
        "favorites": 1,
        "duration": "1:32",
        "pubdate": 1684929956
    },
    {
        "title": "抽到小姨的第一天（神鹤莫迪初体验）全队最高70级",
        "desc": "-",
        "url": "http://www.bilibili.com/video/av569171134",
        "pic": "https://i1.hdslb.com/bfs/archive/258dc8ecbd192346b2d51e30e1aabe29c987f4ca.jpg",
        "author": "Litinblue",
        "play": 208,
        "favorites": 1,
        "duration": "0:51",
        "pubdate": 1680005544
    },
    {
        "title": "迪希雅砂糖也能蒸？夜莫迪砂 17s 矩阵",
        "desc": "极中极大概是 15.",
        "url": "http://www.bilibili.com/video/av865914780",
        "pic": "https://i1.hdslb.com/bfs/archive/ab1b92581a56d3ad95f21d82454998ab6c69dfc0.jpg",
        "author": "初三电波台",
        "play": 421,
        "favorites": 2,
        "duration": "0:25",
        "pubdate": 1678747421
    },
    {
        "title": "《原神》快速稳定蒸夜出伤，[夜万莫迪]小演示",
        "desc": "可惜这个流程吃不到夜兰自己的天赋增伤和万叶2命。\n对单：莫q 迪e 万e吃球 夜eaeqa 万qae↓aa 莫ea 迪aa 夜a到q5秒CD\n对群：迪eaa 莫qa 万叶e↓ 夜eeqa 但是后续水转火可能比较麻烦",
        "url": "http://www.bilibili.com/video/av653142707",
        "pic": "https://i1.hdslb.com/bfs/archive/d231cd1e176c0071bde93aa98a5fcc13c2fbd386.jpg",
        "author": "晓影酥",
        "play": 231,
        "favorites": 0,
        "duration": "0:42",
        "pubdate": 1678253623
    },
    {
        "title": "传统永冻队温神莫迪，一样杀剑鬼",
        "desc": "2+1绫华",
        "url": "http://www.bilibili.com/video/av483188926",
        "pic": "https://i1.hdslb.com/bfs/archive/42b80d9970b8857f22a828ff040726b0dd5d7a7e.jpg",
        "author": "霜月love",
        "play": 166,
        "favorites": 0,
        "duration": "0:52",
        "pubdate": 1678238622
    },
    {
        "title": "【3.4深渊】 首撮一把胡夜莫迪",
        "desc": "视频中迪希雅60未突破，1+1胡桃，2+1夜兰，金箔莫娜。",
        "url": "http://www.bilibili.com/video/av225539097",
        "pic": "https://i1.hdslb.com/bfs/archive/a09069d8019eb3b65584760254477839dc9819d6.jpg",
        "author": "EternalFlower",
        "play": 133,
        "favorites": 0,
        "duration": "3:36",
        "pubdate": 1678022733
    },
    {
        "title": "迪希雅输出最强双c互拐队伍 ——莫迪万班手法尝试",
        "desc": "爆发期：万叶长e双扩散 莫娜核爆 迪希雅吃满buff开q；莫娜重击期： 扩水染火 ，迪希雅e加霸体，莫娜重击输出",
        "url": "http://www.bilibili.com/video/av225421805",
        "pic": "https://i1.hdslb.com/bfs/archive/dacb2dc664ee907b0e60d5fe6c97a6b9c8b3b65c.jpg",
        "author": "子小白-",
        "play": 693,
        "favorites": 3,
        "duration": "0:55",
        "pubdate": 1677844288
    },
    {
        "title": "七圣召唤NGA瑞士轮第5轮 班可岩 vs 砂莫迪 胜 最后一轮拿不到3胜开始整活",
        "desc": "周四晚场 合计2-3 最后32人小组排18",
        "url": "http://www.bilibili.com/video/av523731528",
        "pic": "https://i1.hdslb.com/bfs/archive/11c48cea52016e3e955f0991c5da6c9956f594c5.jpg",
        "author": "大白菜了啊",
        "play": 29,
        "favorites": 0,
        "duration": "8:16",
        "pubdate": 1675355915
    },
    {
        "title": "原神七圣召唤永冻队打双活蒸发队班莫迪",
        "desc": "-",
        "url": "http://www.bilibili.com/video/av307793823",
        "pic": "https://i1.hdslb.com/bfs/archive/76895ad219054f1aa32e4998973afb1945800e7a.jpg",
        "author": "脚滑韵华",
        "play": 22,
        "favorites": 0,
        "duration": "10:49",
        "pubdate": 1673631377
    },
    {
        "title": "【影之诗】灿金鱼vs灾祸水银莫迪凯",
        "desc": "示天龙剑dlc",
        "url": "http://www.bilibili.com/video/av522213459",
        "pic": "https://i1.hdslb.com/bfs/archive/d669822d1425f8656e73b2f14054c8b103d6f636.jpg",
        "author": "murd3r17",
        "play": 16,
        "favorites": 0,
        "duration": "2:41",
        "pubdate": 1672718485
    },
    {
        "title": "三险（紫）一金非保底，莫迪琴七待池里",
        "desc": "点赞祝你单抽出金，永远不歪：）",
        "url": "http://www.bilibili.com/video/av946927156",
        "pic": "https://i1.hdslb.com/bfs/archive/0cc8b11737df99e9674504391a47b5353a8c9113.jpg",
        "author": "疯了天",
        "play": 9,
        "favorites": 1,
        "duration": "1:21",
        "pubdate": 1672235957
    },
    {
        "title": "【影之诗】双职业五费灾祸六费莫迪凯压死弃牌龙",
        "desc": "示天龙剑dlc",
        "url": "http://www.bilibili.com/video/av691664785",
        "pic": "https://i1.hdslb.com/bfs/archive/28aa23c6f3b2e613ddd063afc9eac4b3a1614adc.jpg",
        "author": "murd3r17",
        "play": 66,
        "favorites": 0,
        "duration": "3:44",
        "pubdate": 1671983791
    },
    {
        "title": "皇莫迪vs神芭宵",
        "desc": "-",
        "url": "http://www.bilibili.com/video/av521508916",
        "pic": "https://i1.hdslb.com/bfs/archive/58568c7ef8f07dfdeaab72fbef8090115fcd6ef5.jpg",
        "author": "毛球王官军ティワット",
        "play": 33,
        "favorites": 0,
        "duration": "6:42",
        "pubdate": 1671756311
    },
    {
        "title": "全网最细讨莫迪打神宵重队思路教学",
        "desc": "-",
        "url": "http://www.bilibili.com/video/av733867390",
        "pic": "https://i1.hdslb.com/bfs/archive/78ab92c29315c0d5b76cf0db56be3e4572c61997.jpg",
        "author": "孤单收藏家",
        "play": 40,
        "favorites": 0,
        "duration": "3:10",
        "pubdate": 1671042778
    },
    {
        "title": "胎教级讨莫迪卡组教学，没手也行！",
        "desc": "-",
        "url": "http://www.bilibili.com/video/av733638393",
        "pic": "https://i1.hdslb.com/bfs/archive/4ddb3dcd3ee061e5c9ceabb49baac5e65b08fcbf.jpg",
        "author": "孤单收藏家",
        "play": 165,
        "favorites": 2,
        "duration": "8:27",
        "pubdate": 1670870095
    },
    {
        "title": "先被偷一人后看岩丘丘王双岩队如何打赢讨莫迪",
        "desc": "没想到匹配到了我推荐的卡组\n刚好试试岩丘王双岩队的强度",
        "url": "http://www.bilibili.com/video/av476153704",
        "pic": "https://i1.hdslb.com/bfs/archive/19ecb69c1f3e1785d5ec6d179dce480c51fa94c0.jpg",
        "author": "孤单收藏家",
        "play": 976,
        "favorites": 0,
        "duration": "5:32",
        "pubdate": 1670834041
    },
    {
        "title": "讨莫迪高质量对战皇柯刻",
        "desc": "中间姥爷切债务人失误了，不然这把能赢\n主要对面前期的牌和骰子太胡了\n我骰子小崩，牌组放了两张胡桃，我到死都没抽到一张",
        "url": "http://www.bilibili.com/video/av518734376",
        "pic": "https://i1.hdslb.com/bfs/archive/39af9f7140507dfdda0a709f1be77db4411efdc5.jpg",
        "author": "孤单收藏家",
        "play": 89,
        "favorites": 1,
        "duration": "4:48",
        "pubdate": 1670766781
    },
    {
        "title": "【原神】七圣召唤 开始就是结束！瞬秒一切的存在莫迪班",
        "desc": "点赞！\n投币！\n三连！\n谢谢支持！",
        "url": "http://www.bilibili.com/video/av476147264",
        "pic": "https://i1.hdslb.com/bfs/archive/ed9a9b559e375a6401e4fb5fae27877a3d17faba.jpg",
        "author": "竹紫夜讲说",
        "play": 173,
        "favorites": 2,
        "duration": "1:39",
        "pubdate": 1670734042
    },
    {
        "title": "讨莫迪后手对战香皇柯",
        "desc": "后手打香皇柯，能看出来对面也是会玩的",
        "url": "http://www.bilibili.com/video/av521068823",
        "pic": "https://i1.hdslb.com/bfs/archive/ed08690c3fada1ff8985ca8ae657261543f417b3.jpg",
        "author": "孤单收藏家",
        "play": 45,
        "favorites": 1,
        "duration": "5:19",
        "pubdate": 1670676275
    }
]